{"frames":{

"apple0":
{
	"frame":{"x":0,"y":0,"w":334,"h":334},
	"rotated":false,
	"trimmed":false,
	"spriteSourceSize":{"x":0,"y":0,"w":334,"y":334},
	"sourceSize":{"w":334,"h":334}
},
"basketLeft":
{
	"frame":{"x":0,"y":336,"w":38,"h":113},
	"rotated":false,
	"trimmed":false,
	"spriteSourceSize":{"x":0,"y":0,"w":38,"y":113},
	"sourceSize":{"w":38,"h":113}
},
"basketRight":
{
	"frame":{"x":336,"y":0,"w":38,"h":113},
	"rotated":false,
	"trimmed":false,
	"spriteSourceSize":{"x":0,"y":0,"w":38,"y":113},
	"sourceSize":{"w":38,"h":113}
},
"aim":
{
	"frame":{"x":376,"y":0,"w":33,"h":32},
	"rotated":false,
	"trimmed":false,
	"spriteSourceSize":{"x":0,"y":0,"w":33,"y":32},
	"sourceSize":{"w":33,"h":32}
},
"basketMid":
{
	"frame":{"x":40,"y":336,"w":27,"h":113},
	"rotated":false,
	"trimmed":false,
	"spriteSourceSize":{"x":0,"y":0,"w":27,"y":113},
	"sourceSize":{"w":27,"h":113}
},
"sachockPoleMiddle":
{
	"frame":{"x":69,"y":336,"w":24,"h":11},
	"rotated":false,
	"trimmed":false,
	"spriteSourceSize":{"x":0,"y":0,"w":24,"y":11},
	"sourceSize":{"w":24,"h":11}
},
"basketEnterBackMid":
{
	"frame":{"x":376,"y":34,"w":19,"h":43},
	"rotated":false,
	"trimmed":false,
	"spriteSourceSize":{"x":0,"y":0,"w":19,"y":43},
	"sourceSize":{"w":19,"h":43}
},
"basketEnterFrontMid":
{
	"frame":{"x":411,"y":0,"w":19,"h":31},
	"rotated":false,
	"trimmed":false,
	"spriteSourceSize":{"x":0,"y":0,"w":19,"y":31},
	"sourceSize":{"w":19,"h":31}
},
"basketEnterBackLeft":
{
	"frame":{"x":69,"y":349,"w":16,"h":43},
	"rotated":false,
	"trimmed":false,
	"spriteSourceSize":{"x":0,"y":0,"w":16,"y":43},
	"sourceSize":{"w":16,"h":43}
},
"basketEnterBackRight":
{
	"frame":{"x":397,"y":34,"w":16,"h":43},
	"rotated":false,
	"trimmed":false,
	"spriteSourceSize":{"x":0,"y":0,"w":16,"y":43},
	"sourceSize":{"w":16,"h":43}
},
"basketEnterFrontLeft":
{
	"frame":{"x":95,"y":336,"w":16,"h":31},
	"rotated":false,
	"trimmed":false,
	"spriteSourceSize":{"x":0,"y":0,"w":16,"y":31},
	"sourceSize":{"w":16,"h":31}
},
"basketEnterFrontRight":
{
	"frame":{"x":432,"y":0,"w":16,"h":31},
	"rotated":false,
	"trimmed":false,
	"spriteSourceSize":{"x":0,"y":0,"w":16,"y":31},
	"sourceSize":{"w":16,"h":31}
},
"sachockPoleBottom":
{
	"frame":{"x":113,"y":336,"w":11,"h":11},
	"rotated":false,
	"trimmed":false,
	"spriteSourceSize":{"x":0,"y":0,"w":11,"y":11},
	"sourceSize":{"w":11,"h":11}
}
}}
